odoo/addons/product_drained_weight/README.rst
odoo/addons/product_drained_weight/__init__.py
odoo/addons/product_drained_weight/__manifest__.py
odoo/addons/product_drained_weight/i18n/es.po
odoo/addons/product_drained_weight/i18n/it.po
odoo/addons/product_drained_weight/i18n/product_drained_weight.pot
odoo/addons/product_drained_weight/models/__init__.py
odoo/addons/product_drained_weight/models/product_product.py
odoo/addons/product_drained_weight/models/product_template.py
odoo/addons/product_drained_weight/readme/CONTRIBUTORS.md
odoo/addons/product_drained_weight/readme/DESCRIPTION.md
odoo/addons/product_drained_weight/readme/USAGE.md
odoo/addons/product_drained_weight/static/description/icon.png
odoo/addons/product_drained_weight/static/description/index.html
odoo/addons/product_drained_weight/tests/__init__.py
odoo/addons/product_drained_weight/tests/test_product_drained_weight.py
odoo/addons/product_drained_weight/views/view_product_product.xml
odoo/addons/product_drained_weight/views/view_product_template.xml
odoo_addon_product_drained_weight-18.0.1.0.0.2.dist-info/METADATA
odoo_addon_product_drained_weight-18.0.1.0.0.2.dist-info/WHEEL
odoo_addon_product_drained_weight-18.0.1.0.0.2.dist-info/top_level.txt
odoo_addon_product_drained_weight-18.0.1.0.0.2.dist-info/RECORD
