Metadata-Version: 2.1
Name: odoo-addon-product_drained_weight
Version: 18.0.1.0.0.2
Requires-Python: >=3.10
Requires-Dist: odoo-addon-product_net_weight==18.0.*
Requires-Dist: odoo==18.0.*
Summary: Add 'Drained Weight' on product models
Home-page: https://github.com/OCA/product-attribute
License: AGPL-3
Author: Tecnativa,Odoo Community Association (OCA)
Author-email: support@odoo-community.org
Classifier: Programming Language :: Python
Classifier: Framework :: Odoo
Classifier: Framework :: Odoo :: 18.0
Classifier: License :: OSI Approved :: GNU Affero General Public License v3
